[{"s":2,"a":96,"i":14,"text":"سَنَةٍۢ","lemma":"سَنَة","gloss":"year(s)","glossMs":"tahun"},{"s":5,"a":26,"i":6,"text":"سَنَةًۭ ۛ","lemma":"سَنَة","gloss":"years","glossMs":"tahun"},{"s":7,"a":130,"i":5,"text":"بِٱلسِّنِينَ","lemma":"سِنِين","gloss":"with years (of famine)","glossMs":"dengan beberapa tahun"},{"s":10,"a":5,"i":12,"text":"ٱلسِّنِينَ","lemma":"سِنِين","gloss":"(of) the years","glossMs":"tahun"},{"s":12,"a":42,"i":18,"text":"سِنِينَ","lemma":"سِنِين","gloss":"years","glossMs":"tahun"},{"s":12,"a":47,"i":4,"text":"سِنِينَ","lemma":"سِنِين","gloss":"years","glossMs":"tahun"},{"s":17,"a":12,"i":18,"text":"ٱلسِّنِينَ","lemma":"سِنِين","gloss":"(of) the years","glossMs":"tahun-tahun"},{"s":18,"a":11,"i":6,"text":"سِنِينَ","lemma":"سِنِين","gloss":"years ","glossMs":"beberapa tahun"},{"s":18,"a":25,"i":6,"text":"سِنِينَ","lemma":"سِنِين","gloss":"years","glossMs":"beberapa tahun"},{"s":20,"a":40,"i":26,"text":"سِنِينَ","lemma":"سِنِين","gloss":"(some) years","glossMs":"beberapa tahun"},{"s":22,"a":47,"i":12,"text":"سَنَةٍۢ","lemma":"سَنَة","gloss":"year(s)","glossMs":"tahun"},{"s":23,"a":112,"i":7,"text":"سِنِينَ","lemma":"سِنِين","gloss":"(of) years","glossMs":"tahun"},{"s":24,"a":43,"i":35,"text":"سَنَا","lemma":"سَنا","gloss":"(the) flash","glossMs":"cahaya"},{"s":26,"a":18,"i":10,"text":"سِنِينَ","lemma":"سِنِين","gloss":"years","glossMs":"beberapa tahun"},{"s":26,"a":205,"i":4,"text":"سِنِينَ","lemma":"سِنِين","gloss":"(for) years","glossMs":"bertahun-tahun"},{"s":29,"a":14,"i":9,"text":"سَنَةٍ","lemma":"سَنَة","gloss":"year(s)","glossMs":"tahun"},{"s":30,"a":4,"i":3,"text":"سِنِينَ ۗ","lemma":"سِنِين","gloss":"years","glossMs":"tahun"},{"s":32,"a":5,"i":15,"text":"سَنَةٍۢ","lemma":"سَنَة","gloss":"years","glossMs":"tahun"},{"s":46,"a":15,"i":20,"text":"سَنَةًۭ","lemma":"سَنَة","gloss":"year(s)","glossMs":"tahun"},{"s":70,"a":4,"i":11,"text":"سَنَةٍۢ","lemma":"سَنَة","gloss":"year(s)","glossMs":"tahun"}]