[{"s":2,"a":30,"i":17,"text":"ٱلدِّمَآءَ","lemma":"دَم","gloss":"[the] blood[s]","glossMs":"darah"},{"s":2,"a":84,"i":6,"text":"دِمَآءَكُمْ","lemma":"دَم","gloss":"your blood","glossMs":"darahmu"},{"s":2,"a":173,"i":5,"text":"وَٱلدَّمَ","lemma":"دَم","gloss":"and [the] blood","glossMs":"dan darah"},{"s":5,"a":3,"i":4,"text":"وَٱلدَّمُ","lemma":"دَم","gloss":"and the blood","glossMs":"dan darah"},{"s":6,"a":145,"i":17,"text":"دَمًۭا","lemma":"دَم","gloss":"blood","glossMs":"darah"},{"s":7,"a":133,"i":7,"text":"وَٱلدَّمَ","lemma":"دَم","gloss":"and the blood","glossMs":"dan darah"},{"s":12,"a":18,"i":4,"text":"بِدَمٍۢ","lemma":"دَم","gloss":"with false blood","glossMs":"dengan darah"},{"s":16,"a":66,"i":13,"text":"وَدَمٍۢ","lemma":"دَم","gloss":"and blood","glossMs":"dan darah"},{"s":16,"a":115,"i":5,"text":"وَٱلدَّمَ","lemma":"دَم","gloss":"and the blood","glossMs":"dan darah"},{"s":22,"a":37,"i":6,"text":"دِمَآؤُهَا","lemma":"دَم","gloss":"their blood","glossMs":"darahnya"}]