[{"s":7,"a":98,"i":7,"text":"ضُحًۭى","lemma":"ضُحًى","gloss":"(in) daylight","glossMs":"pada waktu pagi"},{"s":20,"a":59,"i":8,"text":"ضُحًۭى","lemma":"ضُحًى","gloss":"(at) forenoon","glossMs":"waktu dhuha"},{"s":20,"a":119,"i":6,"text":"تَضْحَىٰ","lemma":"تَضْحَى","gloss":"exposed to the sun's heat","glossMs":"kena panas matahari"},{"s":79,"a":29,"i":4,"text":"ضُحَىٰهَا","lemma":"ضُحًى","gloss":"its brightness","glossMs":"paginya/siangnya"},{"s":79,"a":46,"i":9,"text":"ضُحَىٰهَا","lemma":"ضُحًى","gloss":"a morning thereof","glossMs":"pagi harinya"},{"s":91,"a":1,"i":2,"text":"وَضُحَىٰهَا","lemma":"ضُحًى","gloss":"and its brightness","glossMs":"dan cahayanya pagi hari"},{"s":93,"a":1,"i":1,"text":"وَٱلضُّحَىٰ","lemma":"ضُحًى","gloss":"By the morning brightness","glossMs":"demi matahari naik"}]