[{"s":2,"a":26,"i":9,"text":"بَعُوضَةًۭ","lemma":"بَعُوضَة","gloss":"(of) a mosquito"},{"s":2,"a":36,"i":10,"text":"بَعْضُكُمْ","lemma":"بَعْض","gloss":"some of you"},{"s":2,"a":36,"i":11,"text":"لِبَعْضٍ","lemma":"بَعْض","gloss":"to others"},{"s":2,"a":73,"i":3,"text":"بِبَعْضِهَا ۚ","lemma":"بَعْض","gloss":"with a part of it"},{"s":2,"a":76,"i":9,"text":"بَعْضُهُمْ","lemma":"بَعْض","gloss":"some of them"},{"s":2,"a":76,"i":11,"text":"بَعْضٍۢ","lemma":"بَعْض","gloss":"some (others)"},{"s":2,"a":85,"i":24,"text":"بِبَعْضِ","lemma":"بَعْض","gloss":"in part (of)"},{"s":2,"a":85,"i":27,"text":"بِبَعْضٍۢ ۚ","lemma":"بَعْض","gloss":"in part"},{"s":2,"a":145,"i":16,"text":"بَعْضُهُم","lemma":"بَعْض","gloss":"some of them"},{"s":2,"a":145,"i":19,"text":"بَعْضٍۢ ۚ","lemma":"بَعْض","gloss":"(of each) other"},{"s":2,"a":251,"i":18,"text":"بَعْضَهُم","lemma":"بَعْض","gloss":"some of them"},{"s":2,"a":251,"i":19,"text":"بِبَعْضٍۢ","lemma":"بَعْض","gloss":"with others"},{"s":2,"a":253,"i":4,"text":"بَعْضَهُمْ","lemma":"بَعْض","gloss":"some of them"},{"s":2,"a":253,"i":6,"text":"بَعْضٍۢ ۘ","lemma":"بَعْض","gloss":"others"},{"s":2,"a":253,"i":12,"text":"بَعْضَهُمْ","lemma":"بَعْض","gloss":"some of them"},{"s":2,"a":259,"i":30,"text":"بَعْضَ","lemma":"بَعْض","gloss":"a part"},{"s":2,"a":283,"i":12,"text":"بَعْضُكُم","lemma":"بَعْض","gloss":"one of you"},{"s":2,"a":283,"i":13,"text":"بَعْضًۭا","lemma":"بَعْض","gloss":"(to) another"},{"s":3,"a":34,"i":2,"text":"بَعْضُهَا","lemma":"بَعْض","gloss":"some of them"},{"s":3,"a":34,"i":4,"text":"بَعْضٍۢ ۗ","lemma":"بَعْض","gloss":"others"},{"s":3,"a":50,"i":9,"text":"بَعْضَ","lemma":"بَعْض","gloss":"some"},{"s":3,"a":64,"i":20,"text":"بَعْضُنَا","lemma":"بَعْض","gloss":"some of us"},{"s":3,"a":64,"i":21,"text":"بَعْضًا","lemma":"بَعْض","gloss":"(to) others"},{"s":3,"a":155,"i":11,"text":"بِبَعْضِ","lemma":"بَعْض","gloss":"for some"},{"s":3,"a":195,"i":14,"text":"بَعْضُكُم","lemma":"بَعْض","gloss":"each of you"},{"s":3,"a":195,"i":16,"text":"بَعْضٍۢ ۖ","lemma":"بَعْض","gloss":"(the) other"},{"s":4,"a":19,"i":14,"text":"بِبَعْضِ","lemma":"بَعْض","gloss":"a part"},{"s":4,"a":21,"i":5,"text":"بَعْضُكُمْ","lemma":"بَعْض","gloss":"one of you"},{"s":4,"a":21,"i":7,"text":"بَعْضٍۢ","lemma":"بَعْض","gloss":"another"},{"s":4,"a":25,"i":20,"text":"بَعْضُكُم","lemma":"بَعْض","gloss":"You"},{"s":4,"a":25,"i":22,"text":"بَعْضٍۢ ۚ","lemma":"بَعْض","gloss":"(one) another"},{"s":4,"a":32,"i":7,"text":"بَعْضَكُمْ","lemma":"بَعْض","gloss":"some of you"},{"s":4,"a":32,"i":9,"text":"بَعْضٍۢ ۚ","lemma":"بَعْض","gloss":"others"},{"s":4,"a":34,"i":8,"text":"بَعْضَهُمْ","lemma":"بَعْض","gloss":"some of them"},{"s":4,"a":34,"i":10,"text":"بَعْضٍۢ","lemma":"بَعْض","gloss":"others"},{"s":4,"a":150,"i":14,"text":"بِبَعْضٍۢ","lemma":"بَعْض","gloss":"in some"},{"s":4,"a":150,"i":16,"text":"بِبَعْضٍۢ","lemma":"بَعْض","gloss":"in others"},{"s":5,"a":49,"i":14,"text":"بَعْضِ","lemma":"بَعْض","gloss":"some"},{"s":5,"a":49,"i":27,"text":"بِبَعْضِ","lemma":"بَعْض","gloss":"for some"},{"s":5,"a":51,"i":9,"text":"بَعْضُهُمْ","lemma":"بَعْض","gloss":"Some of them"},{"s":5,"a":51,"i":11,"text":"بَعْضٍۢ ۚ","lemma":"بَعْض","gloss":"(to) others"},{"s":6,"a":53,"i":3,"text":"بَعْضَهُم","lemma":"بَعْض","gloss":"some of them"},{"s":6,"a":53,"i":4,"text":"بِبَعْضٍۢ","lemma":"بَعْض","gloss":"with others"},{"s":6,"a":65,"i":19,"text":"بَعْضَكُم","lemma":"بَعْض","gloss":"some of you"},{"s":6,"a":65,"i":21,"text":"بَعْضٍ ۗ","lemma":"بَعْض","gloss":"(of) others"},{"s":6,"a":112,"i":10,"text":"بَعْضُهُمْ","lemma":"بَعْض","gloss":"some of them"},{"s":6,"a":112,"i":12,"text":"بَعْضٍۢ","lemma":"بَعْض","gloss":"others"},{"s":6,"a":128,"i":16,"text":"بَعْضُنَا","lemma":"بَعْض","gloss":"some of us"},{"s":6,"a":128,"i":17,"text":"بِبَعْضٍۢ","lemma":"بَعْض","gloss":"by others"},{"s":6,"a":129,"i":3,"text":"بَعْضَ","lemma":"بَعْض","gloss":"some (of)"},{"s":6,"a":129,"i":5,"text":"بَعْضًۢا","lemma":"بَعْض","gloss":"(to) others"},{"s":6,"a":158,"i":12,"text":"بَعْضُ","lemma":"بَعْض","gloss":"some (of)"},{"s":6,"a":158,"i":17,"text":"بَعْضُ","lemma":"بَعْض","gloss":"some (of)"},{"s":6,"a":165,"i":7,"text":"بَعْضَكُمْ","lemma":"بَعْض","gloss":"some of you"},{"s":6,"a":165,"i":9,"text":"بَعْضٍۢ","lemma":"بَعْض","gloss":"others"},{"s":7,"a":24,"i":3,"text":"بَعْضُكُمْ","lemma":"بَعْض","gloss":"some of you"},{"s":7,"a":24,"i":4,"text":"لِبَعْضٍ","lemma":"بَعْض","gloss":"to some others"},{"s":8,"a":37,"i":8,"text":"بَعْضَهُۥ","lemma":"بَعْض","gloss":"some of them"},{"s":8,"a":37,"i":10,"text":"بَعْضٍۢ","lemma":"بَعْض","gloss":"others"},{"s":8,"a":72,"i":15,"text":"بَعْضُهُمْ","lemma":"بَعْض","gloss":"some of them"},{"s":8,"a":72,"i":17,"text":"بَعْضٍۢ ۚ","lemma":"بَعْض","gloss":"(of) another"},{"s":8,"a":73,"i":3,"text":"بَعْضُهُمْ","lemma":"بَعْض","gloss":"some of them"},{"s":8,"a":73,"i":5,"text":"بَعْضٍ ۚ","lemma":"بَعْض","gloss":"(to) another"},{"s":8,"a":75,"i":12,"text":"بَعْضُهُمْ","lemma":"بَعْض","gloss":"some of them"},{"s":8,"a":75,"i":14,"text":"بِبَعْضٍۢ","lemma":"بَعْض","gloss":"to another"},{"s":9,"a":67,"i":3,"text":"بَعْضُهُم","lemma":"بَعْض","gloss":"some of them"},{"s":9,"a":67,"i":5,"text":"بَعْضٍۢ ۚ","lemma":"بَعْض","gloss":"others"},{"s":9,"a":71,"i":3,"text":"بَعْضُهُمْ","lemma":"بَعْض","gloss":"some of them"},{"s":9,"a":71,"i":5,"text":"بَعْضٍۢ ۚ","lemma":"بَعْض","gloss":"(of) others"},{"s":9,"a":127,"i":6,"text":"بَعْضُهُمْ","lemma":"بَعْض","gloss":"some of them"},{"s":9,"a":127,"i":8,"text":"بَعْضٍ","lemma":"بَعْض","gloss":"others"},{"s":10,"a":46,"i":3,"text":"بَعْضَ","lemma":"بَعْض","gloss":"some"},{"s":11,"a":12,"i":3,"text":"بَعْضَ","lemma":"بَعْض","gloss":"a part"},{"s":11,"a":54,"i":5,"text":"بَعْضُ","lemma":"بَعْض","gloss":"some"},{"s":12,"a":10,"i":12,"text":"بَعْضُ","lemma":"بَعْض","gloss":"some"},{"s":13,"a":4,"i":17,"text":"بَعْضَهَا","lemma":"بَعْض","gloss":"some of them"},{"s":13,"a":4,"i":19,"text":"بَعْضٍۢ","lemma":"بَعْض","gloss":"others"},{"s":13,"a":36,"i":12,"text":"بَعْضَهُۥ ۚ","lemma":"بَعْض","gloss":"a part of it"},{"s":13,"a":40,"i":4,"text":"بَعْضَ","lemma":"بَعْض","gloss":"a part"},{"s":16,"a":71,"i":3,"text":"بَعْضَكُمْ","lemma":"بَعْض","gloss":"some of you"},{"s":16,"a":71,"i":5,"text":"بَعْضٍۢ","lemma":"بَعْض","gloss":"others"},{"s":17,"a":21,"i":4,"text":"بَعْضَهُمْ","lemma":"بَعْض","gloss":"some of them"},{"s":17,"a":21,"i":6,"text":"بَعْضٍۢ ۚ","lemma":"بَعْض","gloss":"others"},{"s":17,"a":55,"i":9,"text":"بَعْضَ","lemma":"بَعْض","gloss":"some"},{"s":17,"a":55,"i":12,"text":"بَعْضٍۢ ۖ","lemma":"بَعْض","gloss":"others"},{"s":17,"a":88,"i":17,"text":"بَعْضُهُمْ","lemma":"بَعْض","gloss":"some of them"},{"s":17,"a":88,"i":18,"text":"لِبَعْضٍۢ","lemma":"بَعْض","gloss":"to some others"},{"s":18,"a":19,"i":14,"text":"بَعْضَ","lemma":"بَعْض","gloss":"a part"},{"s":18,"a":99,"i":2,"text":"بَعْضَهُمْ","lemma":"بَعْض","gloss":"some of them"},{"s":18,"a":99,"i":6,"text":"بَعْضٍۢ ۖ","lemma":"بَعْض","gloss":"others"},{"s":20,"a":123,"i":5,"text":"بَعْضُكُمْ","lemma":"بَعْض","gloss":"some of you"},{"s":20,"a":123,"i":6,"text":"لِبَعْضٍ","lemma":"بَعْض","gloss":"to others"},{"s":22,"a":40,"i":16,"text":"بَعْضَهُم","lemma":"بَعْض","gloss":"some of them"},{"s":22,"a":40,"i":17,"text":"بِبَعْضٍۢ","lemma":"بَعْض","gloss":"by others"},{"s":23,"a":44,"i":12,"text":"بَعْضَهُم","lemma":"بَعْض","gloss":"some of them"},{"s":23,"a":44,"i":13,"text":"بَعْضًۭا","lemma":"بَعْض","gloss":"others"},{"s":23,"a":91,"i":18,"text":"بَعْضُهُمْ","lemma":"بَعْض","gloss":"some of them"},{"s":23,"a":91,"i":20,"text":"بَعْضٍۢ ۚ","lemma":"بَعْض","gloss":"others"},{"s":23,"a":113,"i":5,"text":"بَعْضَ","lemma":"بَعْض","gloss":"a part"},{"s":24,"a":40,"i":15,"text":"بَعْضُهَا","lemma":"بَعْض","gloss":"some of it"},{"s":24,"a":40,"i":17,"text":"بَعْضٍ","lemma":"بَعْض","gloss":"others"},{"s":24,"a":58,"i":39,"text":"بَعْضُكُمْ","lemma":"بَعْض","gloss":"some of you"},{"s":24,"a":58,"i":41,"text":"بَعْضٍۢ ۚ","lemma":"بَعْض","gloss":"others"},{"s":24,"a":62,"i":27,"text":"لِبَعْضِ","lemma":"بَعْض","gloss":"for some"},{"s":24,"a":63,"i":7,"text":"بَعْضِكُم","lemma":"بَعْض","gloss":"(of) some of you"},{"s":24,"a":63,"i":8,"text":"بَعْضًۭا ۚ","lemma":"بَعْض","gloss":"(to) others"},{"s":25,"a":20,"i":14,"text":"بَعْضَكُمْ","lemma":"بَعْض","gloss":"some of you"},{"s":25,"a":20,"i":15,"text":"لِبَعْضٍۢ","lemma":"بَعْض","gloss":"for others"},{"s":26,"a":198,"i":4,"text":"بَعْضِ","lemma":"بَعْض","gloss":"any"},{"s":27,"a":72,"i":7,"text":"بَعْضُ","lemma":"بَعْض","gloss":"some"},{"s":29,"a":25,"i":17,"text":"بَعْضُكُم","lemma":"بَعْض","gloss":"one another"},{"s":29,"a":25,"i":18,"text":"بِبَعْضٍۢ","lemma":"بَعْض","gloss":"one another"},{"s":29,"a":25,"i":20,"text":"بَعْضُكُم","lemma":"بَعْض","gloss":"one another"},{"s":29,"a":25,"i":21,"text":"بَعْضًۭا","lemma":"بَعْض","gloss":"one another"},{"s":30,"a":41,"i":11,"text":"بَعْضَ","lemma":"بَعْض","gloss":"a part"},{"s":33,"a":6,"i":10,"text":"بَعْضُهُمْ","lemma":"بَعْض","gloss":"some of them"},{"s":33,"a":6,"i":12,"text":"بِبَعْضٍۢ","lemma":"بَعْض","gloss":"to another"},{"s":34,"a":31,"i":20,"text":"بَعْضُهُمْ","lemma":"بَعْض","gloss":"some of them"},{"s":34,"a":31,"i":22,"text":"بَعْضٍ","lemma":"بَعْض","gloss":"others"},{"s":34,"a":42,"i":4,"text":"بَعْضُكُمْ","lemma":"بَعْض","gloss":"some of you"},{"s":34,"a":42,"i":5,"text":"لِبَعْضٍۢ","lemma":"بَعْض","gloss":"on others"},{"s":35,"a":40,"i":30,"text":"بَعْضُهُم","lemma":"بَعْض","gloss":"some of them"},{"s":35,"a":40,"i":31,"text":"بَعْضًا","lemma":"بَعْض","gloss":"(to) others"},{"s":37,"a":27,"i":2,"text":"بَعْضُهُمْ","lemma":"بَعْض","gloss":"some of them"},{"s":37,"a":27,"i":4,"text":"بَعْضٍۢ","lemma":"بَعْض","gloss":"others"},{"s":37,"a":50,"i":2,"text":"بَعْضُهُمْ","lemma":"بَعْض","gloss":"some of them"},{"s":37,"a":50,"i":4,"text":"بَعْضٍۢ","lemma":"بَعْض","gloss":"others"},{"s":38,"a":22,"i":12,"text":"بَعْضُنَا","lemma":"بَعْض","gloss":"one of us"},{"s":38,"a":22,"i":14,"text":"بَعْضٍۢ","lemma":"بَعْض","gloss":"another"},{"s":38,"a":24,"i":13,"text":"بَعْضُهُمْ","lemma":"بَعْض","gloss":"some of them"},{"s":38,"a":24,"i":15,"text":"بَعْضٍ","lemma":"بَعْض","gloss":"another"},{"s":40,"a":28,"i":29,"text":"بَعْضُ","lemma":"بَعْض","gloss":"some (of)"},{"s":40,"a":77,"i":8,"text":"بَعْضَ","lemma":"بَعْض","gloss":"some"},{"s":43,"a":32,"i":13,"text":"بَعْضَهُمْ","lemma":"بَعْض","gloss":"some of them"},{"s":43,"a":32,"i":15,"text":"بَعْضٍۢ","lemma":"بَعْض","gloss":"others"},{"s":43,"a":32,"i":18,"text":"بَعْضُهُم","lemma":"بَعْض","gloss":"some of them"},{"s":43,"a":32,"i":19,"text":"بَعْضًۭا","lemma":"بَعْض","gloss":"others"},{"s":43,"a":63,"i":11,"text":"بَعْضَ","lemma":"بَعْض","gloss":"some"},{"s":43,"a":67,"i":3,"text":"بَعْضُهُمْ","lemma":"بَعْض","gloss":"some of them"},{"s":43,"a":67,"i":4,"text":"لِبَعْضٍ","lemma":"بَعْض","gloss":"to others"},{"s":45,"a":19,"i":10,"text":"بَعْضُهُمْ","lemma":"بَعْض","gloss":"some of them"},{"s":45,"a":19,"i":12,"text":"بَعْضٍۢ ۖ","lemma":"بَعْض","gloss":"(of) others"},{"s":47,"a":4,"i":29,"text":"بَعْضَكُم","lemma":"بَعْض","gloss":"some of you"},{"s":47,"a":4,"i":30,"text":"بِبَعْضٍۢ ۗ","lemma":"بَعْض","gloss":"with others"},{"s":47,"a":26,"i":11,"text":"بَعْضِ","lemma":"بَعْض","gloss":"part"},{"s":49,"a":2,"i":15,"text":"بَعْضِكُمْ","lemma":"بَعْض","gloss":"(of) some of you"},{"s":49,"a":2,"i":16,"text":"لِبَعْضٍ","lemma":"بَعْض","gloss":"to others"},{"s":49,"a":12,"i":9,"text":"بَعْضَ","lemma":"بَعْض","gloss":"some"},{"s":49,"a":12,"i":16,"text":"بَّعْضُكُم","lemma":"بَعْض","gloss":"some of you"},{"s":49,"a":12,"i":17,"text":"بَعْضًا ۚ","lemma":"بَعْض","gloss":"(to) others"},{"s":52,"a":25,"i":2,"text":"بَعْضُهُمْ","lemma":"بَعْض","gloss":"some of them"},{"s":52,"a":25,"i":4,"text":"بَعْضٍۢ","lemma":"بَعْض","gloss":"others"},{"s":66,"a":3,"i":5,"text":"بَعْضِ","lemma":"بَعْض","gloss":"one"},{"s":66,"a":3,"i":15,"text":"بَعْضَهُۥ","lemma":"بَعْض","gloss":"a part of it"},{"s":66,"a":3,"i":18,"text":"بَعْضٍۢ ۖ","lemma":"بَعْض","gloss":"a part"},{"s":68,"a":30,"i":2,"text":"بَعْضُهُمْ","lemma":"بَعْض","gloss":"some of them"},{"s":68,"a":30,"i":4,"text":"بَعْضٍۢ","lemma":"بَعْض","gloss":"others"},{"s":69,"a":44,"i":4,"text":"بَعْضَ","lemma":"بَعْض","gloss":"some"}]