[{"s":2,"a":268,"i":3,"text":"ٱلْفَقْرَ","lemma":"فَقْر","gloss":"[the] poverty","glossMs":"kemiskinan"},{"s":2,"a":271,"i":9,"text":"ٱلْفُقَرَآءَ","lemma":"فَقِير","gloss":"(to) the poor","glossMs":"orang-orang fakir"},{"s":2,"a":273,"i":1,"text":"لِلْفُقَرَآءِ","lemma":"فَقِير","gloss":"For the poor","glossMs":"bagi orang-orang fakir"},{"s":3,"a":181,"i":9,"text":"فَقِيرٌۭ","lemma":"فَقِير","gloss":"(is) poor","glossMs":"miskin"},{"s":4,"a":6,"i":26,"text":"فَقِيرًۭا","lemma":"فَقِير","gloss":"poor","glossMs":"fakir/miskin"},{"s":4,"a":135,"i":19,"text":"فَقِيرًۭا","lemma":"فَقِير","gloss":"poor","glossMs":"miskin"},{"s":9,"a":60,"i":3,"text":"لِلْفُقَرَآءِ","lemma":"فَقِير","gloss":"(are) for the poor","glossMs":"untuk orang-orang fakir"},{"s":22,"a":28,"i":20,"text":"ٱلْفَقِيرَ","lemma":"فَقِير","gloss":"the poor","glossMs":"orang-orang yang fakir"},{"s":24,"a":32,"i":10,"text":"فُقَرَآءَ","lemma":"فَقِير","gloss":"poor","glossMs":"fakir"},{"s":28,"a":24,"i":15,"text":"فَقِيرٌۭ","lemma":"فَقِير","gloss":"(in) need","glossMs":"sangat memerlukan"},{"s":35,"a":15,"i":4,"text":"ٱلْفُقَرَآءُ","lemma":"فَقِير","gloss":"(are) those in need","glossMs":"berkeperluan/berkehendak"},{"s":47,"a":38,"i":20,"text":"ٱلْفُقَرَآءُ ۚ","lemma":"فَقِير","gloss":"(are) the needy","glossMs":"fakir/berkeperluan"},{"s":59,"a":8,"i":1,"text":"لِلْفُقَرَآءِ","lemma":"فَقِير","gloss":"For the poor","glossMs":"bagi orang-orang fakir"},{"s":75,"a":25,"i":5,"text":"فَاقِرَةٌۭ","lemma":"فاقِرَة","gloss":"backbreaking","glossMs":"kebinasaan/malapetaka besar"}]