{"p":107,"juz":6,"surahs":[],"firstKey":"5:3","lines":[{"t":"ayah","n":1,"w":[{"c":"ﱁ","fp":107,"k":"5:3","i":1,"u":"حُرِّمَتْ"},{"c":"ﱂ","fp":107,"k":"5:3","i":2,"u":"عَلَيْكُمُ"},{"c":"ﱃ","fp":107,"k":"5:3","i":3,"u":"ٱلْمَيْتَةُ"},{"c":"ﱄ","fp":107,"k":"5:3","i":4,"u":"وَٱلدَّمُ"},{"c":"ﱅ","fp":107,"k":"5:3","i":5,"u":"وَلَحْمُ"},{"c":"ﱆ","fp":107,"k":"5:3","i":6,"u":"ٱلْخِنزِيرِ"},{"c":"ﱇ","fp":107,"k":"5:3","i":7,"u":"وَمَآ"},{"c":"ﱈ","fp":107,"k":"5:3","i":8,"u":"أُهِلَّ"},{"c":"ﱉ","fp":107,"k":"5:3","i":9,"u":"لِغَيْرِ"},{"c":"ﱊ","fp":107,"k":"5:3","i":10,"u":"ٱللَّهِ"},{"c":"ﱋ","fp":107,"k":"5:3","i":11,"u":"بِهِۦ"}]},{"t":"ayah","n":2,"w":[{"c":"ﱌ","fp":107,"k":"5:3","i":12,"u":"وَٱلْمُنْخَنِقَةُ"},{"c":"ﱍ","fp":107,"k":"5:3","i":13,"u":"وَٱلْمَوْقُوذَةُ"},{"c":"ﱎ","fp":107,"k":"5:3","i":14,"u":"وَٱلْمُتَرَدِّيَةُ"},{"c":"ﱏ","fp":107,"k":"5:3","i":15,"u":"وَٱلنَّطِيحَةُ"},{"c":"ﱐ","fp":107,"k":"5:3","i":16,"u":"وَمَآ"},{"c":"ﱑ","fp":107,"k":"5:3","i":17,"u":"أَكَلَ"}]},{"t":"ayah","n":3,"w":[{"c":"ﱒ","fp":107,"k":"5:3","i":18,"u":"ٱلسَّبُعُ"},{"c":"ﱓ","fp":107,"k":"5:3","i":19,"u":"إِلَّا"},{"c":"ﱔ","fp":107,"k":"5:3","i":20,"u":"مَا"},{"c":"ﱕ","fp":107,"k":"5:3","i":21,"u":"ذَكَّيْتُمْ"},{"c":"ﱖ","fp":107,"k":"5:3","i":22,"u":"وَمَا"},{"c":"ﱗ","fp":107,"k":"5:3","i":23,"u":"ذُبِحَ"},{"c":"ﱘ","fp":107,"k":"5:3","i":24,"u":"عَلَى"},{"c":"ﱙ","fp":107,"k":"5:3","i":25,"u":"ٱلنُّصُبِ"},{"c":"ﱚ","fp":107,"k":"5:3","i":26,"u":"وَأَن"},{"c":"ﱛ","fp":107,"k":"5:3","i":27,"u":"تَسْتَقْسِمُوا۟"}]},{"t":"ayah","n":4,"w":[{"c":"ﱜﱝ","fp":107,"k":"5:3","i":28,"u":"بِٱلْأَزْلَـٰمِ ۚ"},{"c":"ﱞ","fp":107,"k":"5:3","i":29,"u":"ذَٰلِكُمْ"},{"c":"ﱟﱠ","fp":107,"k":"5:3","i":30,"u":"فِسْقٌ ۗ"},{"c":"ﱡ","fp":107,"k":"5:3","i":31,"u":"ٱلْيَوْمَ"},{"c":"ﱢ","fp":107,"k":"5:3","i":32,"u":"يَئِسَ"},{"c":"ﱣ","fp":107,"k":"5:3","i":33,"u":"ٱلَّذِينَ"},{"c":"ﱤ","fp":107,"k":"5:3","i":34,"u":"كَفَرُوا۟"},{"c":"ﱥ","fp":107,"k":"5:3","i":35,"u":"مِن"},{"c":"ﱦ","fp":107,"k":"5:3","i":36,"u":"دِينِكُمْ"},{"c":"ﱧ","fp":107,"k":"5:3","i":37,"u":"فَلَا"}]},{"t":"ayah","n":5,"w":[{"c":"ﱨ","fp":107,"k":"5:3","i":38,"u":"تَخْشَوْهُمْ"},{"c":"ﱩﱪ","fp":107,"k":"5:3","i":39,"u":"وَٱخْشَوْنِ ۚ"},{"c":"ﱫ","fp":107,"k":"5:3","i":40,"u":"ٱلْيَوْمَ"},{"c":"ﱬ","fp":107,"k":"5:3","i":41,"u":"أَكْمَلْتُ"},{"c":"ﱭ","fp":107,"k":"5:3","i":42,"u":"لَكُمْ"},{"c":"ﱮ","fp":107,"k":"5:3","i":43,"u":"دِينَكُمْ"},{"c":"ﱯ","fp":107,"k":"5:3","i":44,"u":"وَأَتْمَمْتُ"},{"c":"ﱰ","fp":107,"k":"5:3","i":45,"u":"عَلَيْكُمْ"}]},{"t":"ayah","n":6,"w":[{"c":"ﱱ","fp":107,"k":"5:3","i":46,"u":"نِعْمَتِى"},{"c":"ﱲ","fp":107,"k":"5:3","i":47,"u":"وَرَضِيتُ"},{"c":"ﱳ","fp":107,"k":"5:3","i":48,"u":"لَكُمُ"},{"c":"ﱴ","fp":107,"k":"5:3","i":49,"u":"ٱلْإِسْلَـٰمَ"},{"c":"ﱵﱶ","fp":107,"k":"5:3","i":50,"u":"دِينًۭا ۚ"},{"c":"ﱷ","fp":107,"k":"5:3","i":51,"u":"فَمَنِ"},{"c":"ﱸ","fp":107,"k":"5:3","i":52,"u":"ٱضْطُرَّ"},{"c":"ﱹ","fp":107,"k":"5:3","i":53,"u":"فِى"},{"c":"ﱺ","fp":107,"k":"5:3","i":54,"u":"مَخْمَصَةٍ"}]},{"t":"ayah","n":7,"w":[{"c":"ﱻ","fp":107,"k":"5:3","i":55,"u":"غَيْرَ"},{"c":"ﱼ","fp":107,"k":"5:3","i":56,"u":"مُتَجَانِفٍۢ"},{"c":"ﱽ","fp":107,"k":"5:3","i":57,"u":"لِّإِثْمٍۢ ۙ"},{"c":"ﱾ","fp":107,"k":"5:3","i":58,"u":"فَإِنَّ"},{"c":"ﱿ","fp":107,"k":"5:3","i":59,"u":"ٱللَّهَ"},{"c":"ﲀ","fp":107,"k":"5:3","i":60,"u":"غَفُورٌۭ"},{"c":"ﲁ","fp":107,"k":"5:3","i":61,"u":"رَّحِيمٌۭ"},{"c":"ﲂ","fp":107,"k":"5:3","i":62,"e":1,"u":"٣"},{"c":"ﲃ","fp":107,"k":"5:4","i":1,"u":"يَسْـَٔلُونَكَ"},{"c":"ﲄ","fp":107,"k":"5:4","i":2,"u":"مَاذَآ"}]},{"t":"ayah","n":8,"w":[{"c":"ﲅ","fp":107,"k":"5:4","i":3,"u":"أُحِلَّ"},{"c":"ﲆﲇ","fp":107,"k":"5:4","i":4,"u":"لَهُمْ ۖ"},{"c":"ﲈ","fp":107,"k":"5:4","i":5,"u":"قُلْ"},{"c":"ﲉ","fp":107,"k":"5:4","i":6,"u":"أُحِلَّ"},{"c":"ﲊ","fp":107,"k":"5:4","i":7,"u":"لَكُمُ"},{"c":"ﲋ","fp":107,"k":"5:4","i":8,"u":"ٱلطَّيِّبَـٰتُ ۙ"},{"c":"ﲌ","fp":107,"k":"5:4","i":9,"u":"وَمَا"},{"c":"ﲍ","fp":107,"k":"5:4","i":10,"u":"عَلَّمْتُم"},{"c":"ﲎ","fp":107,"k":"5:4","i":11,"u":"مِّنَ"},{"c":"ﲏ","fp":107,"k":"5:4","i":12,"u":"ٱلْجَوَارِحِ"}]},{"t":"ayah","n":9,"w":[{"c":"ﲐ","fp":107,"k":"5:4","i":13,"u":"مُكَلِّبِينَ"},{"c":"ﲑ","fp":107,"k":"5:4","i":14,"u":"تُعَلِّمُونَهُنَّ"},{"c":"ﲒ","fp":107,"k":"5:4","i":15,"u":"مِمَّا"},{"c":"ﲓ","fp":107,"k":"5:4","i":16,"u":"عَلَّمَكُمُ"},{"c":"ﲔﲕ","fp":107,"k":"5:4","i":17,"u":"ٱللَّهُ ۖ"},{"c":"ﲖ","fp":107,"k":"5:4","i":18,"u":"فَكُلُوا۟"},{"c":"ﲗ","fp":107,"k":"5:4","i":19,"u":"مِمَّآ"},{"c":"ﲘ","fp":107,"k":"5:4","i":20,"u":"أَمْسَكْنَ"},{"c":"ﲙ","fp":107,"k":"5:4","i":21,"u":"عَلَيْكُمْ"}]},{"t":"ayah","n":10,"w":[{"c":"ﲚ","fp":107,"k":"5:4","i":22,"u":"وَٱذْكُرُوا۟"},{"c":"ﲛ","fp":107,"k":"5:4","i":23,"u":"ٱسْمَ"},{"c":"ﲜ","fp":107,"k":"5:4","i":24,"u":"ٱللَّهِ"},{"c":"ﲝﲞ","fp":107,"k":"5:4","i":25,"u":"عَلَيْهِ ۖ"},{"c":"ﲟ","fp":107,"k":"5:4","i":26,"u":"وَٱتَّقُوا۟"},{"c":"ﲠﲡ","fp":107,"k":"5:4","i":27,"u":"ٱللَّهَ ۚ"},{"c":"ﲢ","fp":107,"k":"5:4","i":28,"u":"إِنَّ"},{"c":"ﲣ","fp":107,"k":"5:4","i":29,"u":"ٱللَّهَ"},{"c":"ﲤ","fp":107,"k":"5:4","i":30,"u":"سَرِيعُ"},{"c":"ﲥ","fp":107,"k":"5:4","i":31,"u":"ٱلْحِسَابِ"},{"c":"ﲦ","fp":107,"k":"5:4","i":32,"e":1,"u":"٤"}]},{"t":"ayah","n":11,"w":[{"c":"ﲧ","fp":107,"k":"5:5","i":1,"u":"ٱلْيَوْمَ"},{"c":"ﲨ","fp":107,"k":"5:5","i":2,"u":"أُحِلَّ"},{"c":"ﲩ","fp":107,"k":"5:5","i":3,"u":"لَكُمُ"},{"c":"ﲪﲫ","fp":107,"k":"5:5","i":4,"u":"ٱلطَّيِّبَـٰتُ ۖ"},{"c":"ﲬ","fp":107,"k":"5:5","i":5,"u":"وَطَعَامُ"},{"c":"ﲭ","fp":107,"k":"5:5","i":6,"u":"ٱلَّذِينَ"},{"c":"ﲮ","fp":107,"k":"5:5","i":7,"u":"أُوتُوا۟"},{"c":"ﲯ","fp":107,"k":"5:5","i":8,"u":"ٱلْكِتَـٰبَ"},{"c":"ﲰ","fp":107,"k":"5:5","i":9,"u":"حِلٌّۭ"},{"c":"ﲱ","fp":107,"k":"5:5","i":10,"u":"لَّكُمْ"}]},{"t":"ayah","n":12,"w":[{"c":"ﲲ","fp":107,"k":"5:5","i":11,"u":"وَطَعَامُكُمْ"},{"c":"ﲳ","fp":107,"k":"5:5","i":12,"u":"حِلٌّۭ"},{"c":"ﲴﲵ","fp":107,"k":"5:5","i":13,"u":"لَّهُمْ ۖ"},{"c":"ﲶ","fp":107,"k":"5:5","i":14,"u":"وَٱلْمُحْصَنَـٰتُ"},{"c":"ﲷ","fp":107,"k":"5:5","i":15,"u":"مِنَ"},{"c":"ﲸ","fp":107,"k":"5:5","i":16,"u":"ٱلْمُؤْمِنَـٰتِ"},{"c":"ﲹ","fp":107,"k":"5:5","i":17,"u":"وَٱلْمُحْصَنَـٰتُ"}]},{"t":"ayah","n":13,"w":[{"c":"ﲺ","fp":107,"k":"5:5","i":18,"u":"مِنَ"},{"c":"ﲻ","fp":107,"k":"5:5","i":19,"u":"ٱلَّذِينَ"},{"c":"ﲼ","fp":107,"k":"5:5","i":20,"u":"أُوتُوا۟"},{"c":"ﲽ","fp":107,"k":"5:5","i":21,"u":"ٱلْكِتَـٰبَ"},{"c":"ﲾ","fp":107,"k":"5:5","i":22,"u":"مِن"},{"c":"ﲿ","fp":107,"k":"5:5","i":23,"u":"قَبْلِكُمْ"},{"c":"ﳀ","fp":107,"k":"5:5","i":24,"u":"إِذَآ"},{"c":"ﳁ","fp":107,"k":"5:5","i":25,"u":"ءَاتَيْتُمُوهُنَّ"},{"c":"ﳂ","fp":107,"k":"5:5","i":26,"u":"أُجُورَهُنَّ"}]},{"t":"ayah","n":14,"w":[{"c":"ﳃ","fp":107,"k":"5:5","i":27,"u":"مُحْصِنِينَ"},{"c":"ﳄ","fp":107,"k":"5:5","i":28,"u":"غَيْرَ"},{"c":"ﳅ","fp":107,"k":"5:5","i":29,"u":"مُسَـٰفِحِينَ"},{"c":"ﳆ","fp":107,"k":"5:5","i":30,"u":"وَلَا"},{"c":"ﳇ","fp":107,"k":"5:5","i":31,"u":"مُتَّخِذِىٓ"},{"c":"ﳈﳉ","fp":107,"k":"5:5","i":32,"u":"أَخْدَانٍۢ ۗ"},{"c":"ﳊ","fp":107,"k":"5:5","i":33,"u":"وَمَن"},{"c":"ﳋ","fp":107,"k":"5:5","i":34,"u":"يَكْفُرْ"}]},{"t":"ayah","n":15,"w":[{"c":"ﳌ","fp":107,"k":"5:5","i":35,"u":"بِٱلْإِيمَـٰنِ"},{"c":"ﳍ","fp":107,"k":"5:5","i":36,"u":"فَقَدْ"},{"c":"ﳎ","fp":107,"k":"5:5","i":37,"u":"حَبِطَ"},{"c":"ﳏ","fp":107,"k":"5:5","i":38,"u":"عَمَلُهُۥ"},{"c":"ﳐ","fp":107,"k":"5:5","i":39,"u":"وَهُوَ"},{"c":"ﳑ","fp":107,"k":"5:5","i":40,"u":"فِى"},{"c":"ﳒ","fp":107,"k":"5:5","i":41,"u":"ٱلْـَٔاخِرَةِ"},{"c":"ﳓ","fp":107,"k":"5:5","i":42,"u":"مِنَ"},{"c":"ﳔ","fp":107,"k":"5:5","i":43,"u":"ٱلْخَـٰسِرِينَ"},{"c":"ﳕ","fp":107,"k":"5:5","i":44,"e":1,"u":"٥"}]}]}