{"p":331,"juz":17,"surahs":[],"firstKey":"21:102","lines":[{"t":"ayah","n":1,"w":[{"c":"ﱁ","fp":331,"k":"21:102","i":1,"u":"لَا"},{"c":"ﱂ","fp":331,"k":"21:102","i":2,"u":"يَسْمَعُونَ"},{"c":"ﱃﱄ","fp":331,"k":"21:102","i":3,"u":"حَسِيسَهَا ۖ"},{"c":"ﱅ","fp":331,"k":"21:102","i":4,"u":"وَهُمْ"},{"c":"ﱆ","fp":331,"k":"21:102","i":5,"u":"فِى"},{"c":"ﱇ","fp":331,"k":"21:102","i":6,"u":"مَا"},{"c":"ﱈ","fp":331,"k":"21:102","i":7,"u":"ٱشْتَهَتْ"},{"c":"ﱉ","fp":331,"k":"21:102","i":8,"u":"أَنفُسُهُمْ"}]},{"t":"ayah","n":2,"w":[{"c":"ﱊ","fp":331,"k":"21:102","i":9,"u":"خَـٰلِدُونَ"},{"c":"ﱋ","fp":331,"k":"21:102","i":10,"e":1,"u":"١٠٢"},{"c":"ﱌ","fp":331,"k":"21:103","i":1,"u":"لَا"},{"c":"ﱍ","fp":331,"k":"21:103","i":2,"u":"يَحْزُنُهُمُ"},{"c":"ﱎ","fp":331,"k":"21:103","i":3,"u":"ٱلْفَزَعُ"},{"c":"ﱏ","fp":331,"k":"21:103","i":4,"u":"ٱلْأَكْبَرُ"},{"c":"ﱐ","fp":331,"k":"21:103","i":5,"u":"وَتَتَلَقَّىٰهُمُ"}]},{"t":"ayah","n":3,"w":[{"c":"ﱑ","fp":331,"k":"21:103","i":6,"u":"ٱلْمَلَـٰٓئِكَةُ"},{"c":"ﱒ","fp":331,"k":"21:103","i":7,"u":"هَـٰذَا"},{"c":"ﱓ","fp":331,"k":"21:103","i":8,"u":"يَوْمُكُمُ"},{"c":"ﱔ","fp":331,"k":"21:103","i":9,"u":"ٱلَّذِى"},{"c":"ﱕ","fp":331,"k":"21:103","i":10,"u":"كُنتُمْ"},{"c":"ﱖ","fp":331,"k":"21:103","i":11,"u":"تُوعَدُونَ"},{"c":"ﱗ","fp":331,"k":"21:103","i":12,"e":1,"u":"١٠٣"}]},{"t":"ayah","n":4,"w":[{"c":"ﱘ","fp":331,"k":"21:104","i":1,"u":"يَوْمَ"},{"c":"ﱙ","fp":331,"k":"21:104","i":2,"u":"نَطْوِى"},{"c":"ﱚ","fp":331,"k":"21:104","i":3,"u":"ٱلسَّمَآءَ"},{"c":"ﱛ","fp":331,"k":"21:104","i":4,"u":"كَطَىِّ"},{"c":"ﱜ","fp":331,"k":"21:104","i":5,"u":"ٱلسِّجِلِّ"},{"c":"ﱝﱞ","fp":331,"k":"21:104","i":6,"u":"لِلْكُتُبِ ۚ"},{"c":"ﱟ","fp":331,"k":"21:104","i":7,"u":"كَمَا"},{"c":"ﱠ","fp":331,"k":"21:104","i":8,"u":"بَدَأْنَآ"}]},{"t":"ayah","n":5,"w":[{"c":"ﱡ","fp":331,"k":"21:104","i":9,"u":"أَوَّلَ"},{"c":"ﱢ","fp":331,"k":"21:104","i":10,"u":"خَلْقٍۢ"},{"c":"ﱣﱤ","fp":331,"k":"21:104","i":11,"u":"نُّعِيدُهُۥ ۚ"},{"c":"ﱥ","fp":331,"k":"21:104","i":12,"u":"وَعْدًا"},{"c":"ﱦﱧ","fp":331,"k":"21:104","i":13,"u":"عَلَيْنَآ ۚ"},{"c":"ﱨ","fp":331,"k":"21:104","i":14,"u":"إِنَّا"},{"c":"ﱩ","fp":331,"k":"21:104","i":15,"u":"كُنَّا"},{"c":"ﱪ","fp":331,"k":"21:104","i":16,"u":"فَـٰعِلِينَ"},{"c":"ﱫ","fp":331,"k":"21:104","i":17,"e":1,"u":"١٠٤"},{"c":"ﱬ","fp":331,"k":"21:105","i":1,"u":"وَلَقَدْ"}]},{"t":"ayah","n":6,"w":[{"c":"ﱭ","fp":331,"k":"21:105","i":2,"u":"كَتَبْنَا"},{"c":"ﱮ","fp":331,"k":"21:105","i":3,"u":"فِى"},{"c":"ﱯ","fp":331,"k":"21:105","i":4,"u":"ٱلزَّبُورِ"},{"c":"ﱰ","fp":331,"k":"21:105","i":5,"u":"مِنۢ"},{"c":"ﱱ","fp":331,"k":"21:105","i":6,"u":"بَعْدِ"},{"c":"ﱲ","fp":331,"k":"21:105","i":7,"u":"ٱلذِّكْرِ"},{"c":"ﱳ","fp":331,"k":"21:105","i":8,"u":"أَنَّ"},{"c":"ﱴ","fp":331,"k":"21:105","i":9,"u":"ٱلْأَرْضَ"},{"c":"ﱵ","fp":331,"k":"21:105","i":10,"u":"يَرِثُهَا"}]},{"t":"ayah","n":7,"w":[{"c":"ﱶ","fp":331,"k":"21:105","i":11,"u":"عِبَادِىَ"},{"c":"ﱷ","fp":331,"k":"21:105","i":12,"u":"ٱلصَّـٰلِحُونَ"},{"c":"ﱸ","fp":331,"k":"21:105","i":13,"e":1,"u":"١٠٥"},{"c":"ﱹ","fp":331,"k":"21:106","i":1,"u":"إِنَّ"},{"c":"ﱺ","fp":331,"k":"21:106","i":2,"u":"فِى"},{"c":"ﱻ","fp":331,"k":"21:106","i":3,"u":"هَـٰذَا"},{"c":"ﱼ","fp":331,"k":"21:106","i":4,"u":"لَبَلَـٰغًۭا"},{"c":"ﱽ","fp":331,"k":"21:106","i":5,"u":"لِّقَوْمٍ"}]},{"t":"ayah","n":8,"w":[{"c":"ﱾ","fp":331,"k":"21:106","i":6,"u":"عَـٰبِدِينَ"},{"c":"ﱿ","fp":331,"k":"21:106","i":7,"e":1,"u":"١٠٦"},{"c":"ﲀ","fp":331,"k":"21:107","i":1,"u":"وَمَآ"},{"c":"ﲁ","fp":331,"k":"21:107","i":2,"u":"أَرْسَلْنَـٰكَ"},{"c":"ﲂ","fp":331,"k":"21:107","i":3,"u":"إِلَّا"},{"c":"ﲃ","fp":331,"k":"21:107","i":4,"u":"رَحْمَةًۭ"},{"c":"ﲄ","fp":331,"k":"21:107","i":5,"u":"لِّلْعَـٰلَمِينَ"}]},{"t":"ayah","n":9,"w":[{"c":"ﲅ","fp":331,"k":"21:107","i":6,"e":1,"u":"١٠٧"},{"c":"ﲆ","fp":331,"k":"21:108","i":1,"u":"قُلْ"},{"c":"ﲇ","fp":331,"k":"21:108","i":2,"u":"إِنَّمَا"},{"c":"ﲈ","fp":331,"k":"21:108","i":3,"u":"يُوحَىٰٓ"},{"c":"ﲉ","fp":331,"k":"21:108","i":4,"u":"إِلَىَّ"},{"c":"ﲊ","fp":331,"k":"21:108","i":5,"u":"أَنَّمَآ"},{"c":"ﲋ","fp":331,"k":"21:108","i":6,"u":"إِلَـٰهُكُمْ"},{"c":"ﲌ","fp":331,"k":"21:108","i":7,"u":"إِلَـٰهٌۭ"},{"c":"ﲍﲎ","fp":331,"k":"21:108","i":8,"u":"وَٰحِدٌۭ ۖ"},{"c":"ﲏ","fp":331,"k":"21:108","i":9,"u":"فَهَلْ"}]},{"t":"ayah","n":10,"w":[{"c":"ﲐ","fp":331,"k":"21:108","i":10,"u":"أَنتُم"},{"c":"ﲑ","fp":331,"k":"21:108","i":11,"u":"مُّسْلِمُونَ"},{"c":"ﲒ","fp":331,"k":"21:108","i":12,"e":1,"u":"١٠٨"},{"c":"ﲓ","fp":331,"k":"21:109","i":1,"u":"فَإِن"},{"c":"ﲔ","fp":331,"k":"21:109","i":2,"u":"تَوَلَّوْا۟"},{"c":"ﲕ","fp":331,"k":"21:109","i":3,"u":"فَقُلْ"},{"c":"ﲖ","fp":331,"k":"21:109","i":4,"u":"ءَاذَنتُكُمْ"},{"c":"ﲗ","fp":331,"k":"21:109","i":5,"u":"عَلَىٰ"},{"c":"ﲘﲙ","fp":331,"k":"21:109","i":6,"u":"سَوَآءٍۢ ۖ"}]},{"t":"ayah","n":11,"w":[{"c":"ﲚ","fp":331,"k":"21:109","i":7,"u":"وَإِنْ"},{"c":"ﲛ","fp":331,"k":"21:109","i":8,"u":"أَدْرِىٓ"},{"c":"ﲜ","fp":331,"k":"21:109","i":9,"u":"أَقَرِيبٌ"},{"c":"ﲝ","fp":331,"k":"21:109","i":10,"u":"أَم"},{"c":"ﲞ","fp":331,"k":"21:109","i":11,"u":"بَعِيدٌۭ"},{"c":"ﲟ","fp":331,"k":"21:109","i":12,"u":"مَّا"},{"c":"ﲠ","fp":331,"k":"21:109","i":13,"u":"تُوعَدُونَ"},{"c":"ﲡ","fp":331,"k":"21:109","i":14,"e":1,"u":"١٠٩"},{"c":"ﲢ","fp":331,"k":"21:110","i":1,"u":"إِنَّهُۥ"},{"c":"ﲣ","fp":331,"k":"21:110","i":2,"u":"يَعْلَمُ"}]},{"t":"ayah","n":12,"w":[{"c":"ﲤ","fp":331,"k":"21:110","i":3,"u":"ٱلْجَهْرَ"},{"c":"ﲥ","fp":331,"k":"21:110","i":4,"u":"مِنَ"},{"c":"ﲦ","fp":331,"k":"21:110","i":5,"u":"ٱلْقَوْلِ"},{"c":"ﲧ","fp":331,"k":"21:110","i":6,"u":"وَيَعْلَمُ"},{"c":"ﲨ","fp":331,"k":"21:110","i":7,"u":"مَا"},{"c":"ﲩ","fp":331,"k":"21:110","i":8,"u":"تَكْتُمُونَ"},{"c":"ﲪ","fp":331,"k":"21:110","i":9,"e":1,"u":"١١٠"},{"c":"ﲫ","fp":331,"k":"21:111","i":1,"u":"وَإِنْ"},{"c":"ﲬ","fp":331,"k":"21:111","i":2,"u":"أَدْرِى"}]},{"t":"ayah","n":13,"w":[{"c":"ﲭ","fp":331,"k":"21:111","i":3,"u":"لَعَلَّهُۥ"},{"c":"ﲮ","fp":331,"k":"21:111","i":4,"u":"فِتْنَةٌۭ"},{"c":"ﲯ","fp":331,"k":"21:111","i":5,"u":"لَّكُمْ"},{"c":"ﲰ","fp":331,"k":"21:111","i":6,"u":"وَمَتَـٰعٌ"},{"c":"ﲱ","fp":331,"k":"21:111","i":7,"u":"إِلَىٰ"},{"c":"ﲲ","fp":331,"k":"21:111","i":8,"u":"حِينٍۢ"},{"c":"ﲳ","fp":331,"k":"21:111","i":9,"e":1,"u":"١١١"},{"c":"ﲴ","fp":331,"k":"21:112","i":1,"u":"قَـٰلَ"},{"c":"ﲵ","fp":331,"k":"21:112","i":2,"u":"رَبِّ"},{"c":"ﲶ","fp":331,"k":"21:112","i":3,"u":"ٱحْكُم"}]},{"t":"ayah","n":14,"w":[{"c":"ﲷﲸ","fp":331,"k":"21:112","i":4,"u":"بِٱلْحَقِّ ۗ"},{"c":"ﲹ","fp":331,"k":"21:112","i":5,"u":"وَرَبُّنَا"},{"c":"ﲺ","fp":331,"k":"21:112","i":6,"u":"ٱلرَّحْمَـٰنُ"},{"c":"ﲻ","fp":331,"k":"21:112","i":7,"u":"ٱلْمُسْتَعَانُ"},{"c":"ﲼ","fp":331,"k":"21:112","i":8,"u":"عَلَىٰ"},{"c":"ﲽ","fp":331,"k":"21:112","i":9,"u":"مَا"},{"c":"ﲾ","fp":331,"k":"21:112","i":10,"u":"تَصِفُونَ"},{"c":"ﲿ","fp":331,"k":"21:112","i":11,"e":1,"u":"١١٢"}]}]}